sshyc/__init__.py
sshyc/__main__.py
sshyc/app.py
sshyc-1.0.2.dist-info/LICENSE
sshyc-1.0.2.dist-info/METADATA
sshyc-1.0.2.dist-info/WHEEL
sshyc-1.0.2.dist-info/entry_points.txt
sshyc-1.0.2.dist-info/top_level.txt
sshyc-1.0.2.dist-info/RECORD
