Metadata-Version: 2.1
Name: sshyc
Version: 1.0.2
Summary: SSHYC short for SSH YAML Configuration is tool to make .ssh/config from YAML files.
Home-page: https://github.com/paip-web/sshyc
Author: Patryk Adamczyk
Author-email: patrykadamczyk@paipweb.com
License: MIT
Keywords: ssh tools ssh_config config yaml
Platform: UNKNOWN
Classifier: Development Status :: 5 - Production/Stable
Classifier: Intended Audience :: Developers
Classifier: Intended Audience :: Information Technology
Classifier: Intended Audience :: System Administrators
Classifier: Topic :: Utilities
Classifier: License :: OSI Approved :: MIT License
Classifier: Programming Language :: Python :: 3
Classifier: Programming Language :: Python :: 3 :: Only
Classifier: Operating System :: OS Independent
Classifier: Operating System :: Microsoft :: Windows
Classifier: Operating System :: Microsoft :: Windows :: Windows 7
Classifier: Operating System :: Microsoft :: Windows :: Windows 10
Classifier: Operating System :: POSIX :: Linux
Classifier: Environment :: Console
Requires-Python: ~=3.6
License-File: LICENSE
Requires-Dist: pyyaml
Provides-Extra: setup
Requires-Dist: wheel ; extra == 'setup'
Requires-Dist: twine ; extra == 'setup'
Requires-Dist: collective.checkdocs ; extra == 'setup'
Requires-Dist: bumpversion ; extra == 'setup'
